{
  "constructor": 0,
  "fields": [
    {
      "map": [
        {
          "k": {
            "bytes": "7468726573686f6c6473"
          },
          "v": {
            "map": [
              {
                "k": {
                  "bytes": "7065746974696f6e5f7468726573686f6c64"
                },
                "v": {
                  "int": 150000000
                }
              },
              {
                "k": {
                  "bytes": "6f7261636c655f7468726573686f6c64"
                },
                "v": {
                  "int": 150000000
                }
              },
              {
                "k": {
                  "bytes": "73746172745f706f685f746573745f7468726573686f6c64"
                },
                "v": {
                  "int": 150000000
                }
              },
              {
                "k": {
                  "bytes": "6d696e745f636f685f7468726573686f6c64"
                },
                "v": {
                  "int": 150000000
                }
              },
              {
                "k": {
                  "bytes": "7265766f6b655f636f685f7468726573686f6c64"
                },
                "v": {
                  "int": 150000000
                }
              },
              {
                "k": {
                  "bytes": "657874726163745f7661756c745f7468726573686f6c64"
                },
                "v": {
                  "int": 150000000
                }
              }
            ]
          }
        },
        {
          "k": {
            "bytes": "636f6e747261637473"
          },
          "v": {
            "map": [
              {
                "k": {
                  "bytes": "647265705f6c6f636b5f636f6e7472616374"
                },
                "v": {
                  "bytes": "fdf1f33d453db3db9515dede313807b9669a1f7ee70c98b53c598c87"
                }
              },
              {
                "k": {
                  "bytes": "64616f5f636f6e7472616374"
                },
                "v": {
                  "bytes": "ba58a20573d866649adbf52693cb79218436fd04f4978265a4639399"
                }
              },
              {
                "k": {
                  "bytes": "6f7261636c655f636f6e7472616374"
                },
                "v": {
                  "bytes": "c732b9551940e485ef318b25a61de6b5b6f838d71e71762b8ad69c6f"
                }
              },
              {
                "k": {
                  "bytes": "706f685f6c6f636b5f636f6e7472616374"
                },
                "v": {
                  "bytes": "f10ff41a3e0bdeeec79effe6ae6fd801dde3b334e41918a955150b13"
                }
              },
              {
                "k": {
                  "bytes": "636f685f6c6f636b5f636f6e7472616374"
                },
                "v": {
                  "bytes": "2bcd7b9b373d099b3b43d68316c9ff8be3e54d0d793b018446a7924b"
                }
              },
              {
                "k": {
                  "bytes": "7661756c745f636f6e7472616374"
                },
                "v": {
                  "bytes": "d27d6b66ba97a52dfabc39ab59becd958dc98f1424ef909d40f0c080"
                }
              }
            ]
          }
        },
        {
          "k": {
            "bytes": "66656573"
          },
          "v": {
            "map": [
              {
                "k": {
                  "bytes": "706f685f73746172745f74657374"
                },
                "v": {
                  "int": 1000000
                }
              },
              {
                "k": {
                  "bytes": "706f685f7665726966795f73756363657373"
                },
                "v": {
                  "int": 1000000
                }
              },
              {
                "k": {
                  "bytes": "706f685f7665726966795f6661696c"
                },
                "v": {
                  "int": 1000000
                }
              },
              {
                "k": {
                  "bytes": "636f685f7265766f6b65"
                },
                "v": {
                  "int": 1000000
                }
              },
              {
                "k": {
                  "bytes": "6d696e696d756d5f6c6f76656c616365"
                },
                "v": {
                  "int": 1500000
                }
              }
            ]
          }
        },
        {
          "k": {
            "bytes": "6b657973"
          },
          "v": {
            "map": [
              {
                "k": {
                  "bytes": "776562736974655f6b6579"
                },
                "v": {
                  "bytes": ""
                }
              }
            ]
          }
        }
      ]
    },
    {
      "int": 1
    }
  ]
}